poetry_multiverse_plugin/__init__.py
poetry_multiverse_plugin/cli/__init__.py
poetry_multiverse_plugin/cli/progress.py
poetry_multiverse_plugin/cli/status.py
poetry_multiverse_plugin/cli/utils.py
poetry_multiverse_plugin/commands/__init__.py
poetry_multiverse_plugin/commands/check.py
poetry_multiverse_plugin/commands/info.py
poetry_multiverse_plugin/commands/lock.py
poetry_multiverse_plugin/commands/run.py
poetry_multiverse_plugin/commands/show.py
poetry_multiverse_plugin/commands/workspace.py
poetry_multiverse_plugin/config.py
poetry_multiverse_plugin/dependencies.py
poetry_multiverse_plugin/errors.py
poetry_multiverse_plugin/hooks/__init__.py
poetry_multiverse_plugin/hooks/build.py
poetry_multiverse_plugin/hooks/hook.py
poetry_multiverse_plugin/installers.py
poetry_multiverse_plugin/packages.py
poetry_multiverse_plugin/plugin.py
poetry_multiverse_plugin/publish.py
poetry_multiverse_plugin/py.typed
poetry_multiverse_plugin/workspace.py
poetry_multiverse_plugin-0.2.1.dist-info/LICENSE.txt
poetry_multiverse_plugin-0.2.1.dist-info/METADATA
poetry_multiverse_plugin-0.2.1.dist-info/WHEEL
poetry_multiverse_plugin-0.2.1.dist-info/entry_points.txt
poetry_multiverse_plugin-0.2.1.dist-info/RECORD
