Metadata-Version: 2.1
Name: poetry-multiverse-plugin
Version: 0.2.1
Summary: Workspace support for Poetry
Home-page: https://irregular-expressions.net/multiverse
License: MIT
Keywords: monorepo,poetry,workspace
Author: Wes Miller
Author-email: 37603175+wmiller4@users.noreply.github.com
Requires-Python: >=3.9,<4.0
Classifier: Development Status :: 3 - Alpha
Classifier: Environment :: Plugins
Classifier: License :: OSI Approved :: MIT License
Classifier: Programming Language :: Python :: 3
Classifier: Programming Language :: Python :: 3.9
Classifier: Programming Language :: Python :: 3.10
Classifier: Programming Language :: Python :: 3.11
Classifier: Programming Language :: Python :: 3.12
Classifier: Programming Language :: Python :: 3.13
Classifier: Topic :: Software Development :: Build Tools
Requires-Dist: poetry (>=1.8,<2.0)
Project-URL: Documentation, https://irregular-expressions.net/multiverse
Project-URL: Repository, https://github.com/wmiller4/poetry-multiverse-plugin
